{"_type":"export","__export_format":4,"__export_date":"2022-11-24T05:27:36.704Z","__export_source":"insomnia.desktop.app:v2022.6.0","resources":[{"_id":"req_61aa01a5d94247618061c1a4b2cb89e5","parentId":"fld_d329214e96f64aa98083b7227e56717f","modified":1669266795387,"created":1662185133797,"url":"http://localhost:3000/categories/7bb83198-3783-416e-8b87-a2b42a9e9b1d/properties","name":"Listar todos imóveis da categoria","description":"","method":"GET","body":{},"parameters":[],"headers":[],"authentication":{},"metaSortKey":-1662185133797,"isPrivate":false,"settingStoreCookies":true,"settingSendCookies":true,"settingDisableRenderRequestBody":false,"settingEncodeUrl":true,"settingRebuildPath":true,"settingFollowRedirects":"global","_type":"request"},{"_id":"fld_d329214e96f64aa98083b7227e56717f","parentId":"wrk_002d912e683a47ee8bedc851c7e13838","modified":1662184686138,"created":1662184686138,"name":"category","description":"","environment":{},"environmentPropertyOrder":null,"metaSortKey":-1662184686138,"_type":"request_group"},{"_id":"wrk_002d912e683a47ee8bedc851c7e13838","parentId":null,"modified":1662175199020,"created":1662175199020,"name":"KL Imovveis","description":"","scope":"collection","_type":"workspace"},{"_id":"req_6bdd2dd440c246619a4f49cf037a642d","parentId":"fld_d329214e96f64aa98083b7227e56717f","modified":1662185156425,"created":1662185109956,"url":"http://localhost:3000/categories","name":"listar categorias","description":"","method":"GET","body":{},"parameters":[],"headers":[],"authentication":{},"metaSortKey":-1662185109956,"isPrivate":false,"settingStoreCookies":true,"settingSendCookies":true,"settingDisableRenderRequestBody":false,"settingEncodeUrl":true,"settingRebuildPath":true,"settingFollowRedirects":"global","_type":"request"},{"_id":"req_e7fac2d574b849d899f8f43a747fd7fa","parentId":"fld_d329214e96f64aa98083b7227e56717f","modified":1669266768480,"created":1662185051042,"url":"http://localhost:3000/categories","name":"Criar Categoria","description":"","method":"POST","body":{"mimeType":"application/json","text":"{\n\t\"name\" : \"mansão\"\n}"},"parameters":[],"headers":[{"name":"Content-Type","value":"application/json","id":"pair_6e94a784863641d4affa29bd9ecc90aa"}],"authentication":{"type":"bearer","token":"{% response 'body', 'req_688cbd5d75bf4901a6dd45e631fe2a09', 'b64::JC50b2tlbg==::46b', 'always', 60 %}","disabled":false},"metaSortKey":-1662185051042,"isPrivate":false,"settingStoreCookies":true,"settingSendCookies":true,"settingDisableRenderRequestBody":false,"settingEncodeUrl":true,"settingRebuildPath":true,"settingFollowRedirects":"global","_type":"request"},{"_id":"req_688cbd5d75bf4901a6dd45e631fe2a09","parentId":"fld_7218cb3f42d14c4d8a45e365294f8c28","modified":1669266629614,"created":1662184889477,"url":"http://localhost:3000/login","name":"Logar User Adm","description":"","method":"POST","body":{"mimeType":"application/json","text":"{\n\t\"email\" : \"nando@kenzie.com\",\n\t\"password\": \"1234\"\n}"},"parameters":[],"headers":[{"name":"Content-Type","value":"application/json","id":"pair_f1cdc6752fdf4ce3ace1221756da86bd"}],"authentication":{},"metaSortKey":-1662184889477,"isPrivate":false,"settingStoreCookies":true,"settingSendCookies":true,"settingDisableRenderRequestBody":false,"settingEncodeUrl":true,"settingRebuildPath":true,"settingFollowRedirects":"global","_type":"request"},{"_id":"fld_7218cb3f42d14c4d8a45e365294f8c28","parentId":"wrk_002d912e683a47ee8bedc851c7e13838","modified":1662183514586,"created":1662183514586,"name":"Login","description":"","environment":{},"environmentPropertyOrder":null,"metaSortKey":-1662183514586,"_type":"request_group"},{"_id":"req_8e28e75e525e4b4eb4412ecac676c864","parentId":"fld_7218cb3f42d14c4d8a45e365294f8c28","modified":1669266705449,"created":1669266600630,"url":"http://localhost:3000/login","name":"Logar User Normal","description":"","method":"POST","body":{"mimeType":"application/json","text":"{\n\t\"email\" : \"lilith@kenzie.com\",\n\t\"password\": \"1234\"\n}"},"parameters":[],"headers":[{"name":"Content-Type","value":"application/json","id":"pair_f1cdc6752fdf4ce3ace1221756da86bd"}],"authentication":{},"metaSortKey":-1662184823513,"isPrivate":false,"settingStoreCookies":true,"settingSendCookies":true,"settingDisableRenderRequestBody":false,"settingEncodeUrl":true,"settingRebuildPath":true,"settingFollowRedirects":"global","_type":"request"},{"_id":"req_5352405ccacd4a6fab1f3ccf5d621f40","parentId":"fld_91318f00c20f41a9a6085fd0c826a466","modified":1669267008110,"created":1662184757549,"url":"http://localhost:3000/schedules/properties/4c9e4178-94d8-465b-a317-06554e4e6aa7","name":"listar agendamentos de um imovel","description":"","method":"GET","body":{},"parameters":[],"headers":[],"authentication":{"type":"bearer","token":"{% response 'body', 'req_688cbd5d75bf4901a6dd45e631fe2a09', 'b64::JC50b2tlbg==::46b', 'always', 60 %}"},"metaSortKey":-1662184757549,"isPrivate":false,"settingStoreCookies":true,"settingSendCookies":true,"settingDisableRenderRequestBody":false,"settingEncodeUrl":true,"settingRebuildPath":true,"settingFollowRedirects":"global","_type":"request"},{"_id":"fld_91318f00c20f41a9a6085fd0c826a466","parentId":"wrk_002d912e683a47ee8bedc851c7e13838","modified":1662183405911,"created":1662183405911,"name":"Schedules","description":"","environment":{},"environmentPropertyOrder":null,"metaSortKey":-1662183405911,"_type":"request_group"},{"_id":"req_2b0c767282b2499d8e2898faedd1f65f","parentId":"fld_91318f00c20f41a9a6085fd0c826a466","modified":1669266993356,"created":1662184689293,"url":"http://localhost:3000/schedules","name":"Create Schedule","description":"","method":"POST","body":{"mimeType":"application/json","text":"{\n\t\t\"userId\" : \"8c87b437-81cf-4f8b-92ca-ba4cd20abd7c\",\n\t\"propertyId\" : \"4c9e4178-94d8-465b-a317-06554e4e6aa7\",\n\t\"date\": \"2022/09/12\",\n\t\"hour\" : \"13:30\"\n\t\n\n}"},"parameters":[],"headers":[{"name":"Content-Type","value":"application/json","id":"pair_2e35f3272ad3404e8b9665e78f77cbbd"}],"authentication":{"type":"bearer","token":"{% response 'body', 'req_688cbd5d75bf4901a6dd45e631fe2a09', 'b64::JC50b2tlbg==::46b', 'always', 60 %}"},"metaSortKey":-1662184689293,"isPrivate":false,"settingStoreCookies":true,"settingSendCookies":true,"settingDisableRenderRequestBody":false,"settingEncodeUrl":true,"settingRebuildPath":true,"settingFollowRedirects":"global","_type":"request"},{"_id":"req_af74a6ee700d4325a330fe6afcff3424","parentId":"fld_fb0436933ea24b5f8a0b50ad333b5809","modified":1669266806638,"created":1662185385815,"url":"http://localhost:3000/properties","name":"Criar Imóveis","description":"","method":"POST","body":{"mimeType":"application/json","text":"{\n\t\"value\" : 1650000,\n\t\"size\" : 46,\n\t\"categoryId\" : \"7bb83198-3783-416e-8b87-a2b42a9e9b1d\" ,\n\t\"address\" : {\n\t\t\"district\" : \"Jardim Europa\" ,\n\t\t\"zipCode\" : \"01916090\",\n\t\t\"number\" : \"79\",\n\t\t\"city\" : \"Rua Alaska\",\n\t\t\"state\": \"SP\"\n\t\t}\n\t\n}"},"parameters":[],"headers":[{"name":"Content-Type","value":"application/json","id":"pair_7392564d8e1e47959125795b0f9d2ee7"}],"authentication":{"type":"bearer","token":"{% response 'body', 'req_688cbd5d75bf4901a6dd45e631fe2a09', 'b64::JC50b2tlbg==::46b', 'always', 60 %}"},"metaSortKey":-1662185385815,"isPrivate":false,"settingStoreCookies":true,"settingSendCookies":true,"settingDisableRenderRequestBody":false,"settingEncodeUrl":true,"settingRebuildPath":true,"settingFollowRedirects":"global","_type":"request"},{"_id":"fld_fb0436933ea24b5f8a0b50ad333b5809","parentId":"wrk_002d912e683a47ee8bedc851c7e13838","modified":1662183398959,"created":1662183398959,"name":"Propertys","description":"","environment":{},"environmentPropertyOrder":null,"metaSortKey":-1662183398959,"_type":"request_group"},{"_id":"req_8aeea9eeac4c4b2ea3021b43204a0eb9","parentId":"fld_fb0436933ea24b5f8a0b50ad333b5809","modified":1662185393142,"created":1662185370100,"url":"http://localhost:3000/properties","name":"listar imóveis","description":"","method":"GET","body":{},"parameters":[],"headers":[],"authentication":{},"metaSortKey":-1662185370100,"isPrivate":false,"settingStoreCookies":true,"settingSendCookies":true,"settingDisableRenderRequestBody":false,"settingEncodeUrl":true,"settingRebuildPath":true,"settingFollowRedirects":"global","_type":"request"},{"_id":"req_620f45a7d95a42ce89669e4ce846800c","parentId":"fld_df69bce5d0924eee9e699baa6a30527f","modified":1662333829069,"created":1662183733519,"url":"http://localhost:3000/users/34131eb3-3fa3-4cdb-96c2-cac16126b898","name":"Deletar usuário (tornar inativo)","description":"","method":"DELETE","body":{},"parameters":[],"headers":[],"authentication":{"type":"bearer","token":"eyJhbGciOiJIUzI1NiIsInR5cCI6IkpXVCJ9.eyJpc0FkbSI6dHJ1ZSwiaWQiOiJjMTMxNzdjOS03MGFmLTQ2ZGQtODQ5ZC0zOTExZTU1YWI5OGEiLCJpYXQiOjE2NjIzMzM3OTEsImV4cCI6MTY2MjQyMDE5MX0.kII467Sz38dxoKpwyyjmfYaV85ep6TIqh7CB8D0ldXw"},"metaSortKey":-1662183733519,"isPrivate":false,"settingStoreCookies":true,"settingSendCookies":true,"settingDisableRenderRequestBody":false,"settingEncodeUrl":true,"settingRebuildPath":true,"settingFollowRedirects":"global","_type":"request"},{"_id":"fld_df69bce5d0924eee9e699baa6a30527f","parentId":"wrk_002d912e683a47ee8bedc851c7e13838","modified":1662175206514,"created":1662175206514,"name":"Users","description":"","environment":{},"environmentPropertyOrder":null,"metaSortKey":-1662175206514,"_type":"request_group"},{"_id":"req_9c77cdd976464a699fc7c11f14831a74","parentId":"fld_df69bce5d0924eee9e699baa6a30527f","modified":1669266635918,"created":1662179376965,"url":"http://localhost:3000/users","name":"listar usuários","description":"","method":"GET","body":{},"parameters":[],"headers":[{"id":"pair_c5ec930b85fb4598917c8fa5e6c6beaf","name":"","value":"","description":""}],"authentication":{"type":"bearer","token":"{% response 'body', 'req_688cbd5d75bf4901a6dd45e631fe2a09', 'b64::JC50b2tlbg==::46b', 'always', 60 %}","disabled":false,"prefix":""},"metaSortKey":-1662179376965,"isPrivate":false,"settingStoreCookies":true,"settingSendCookies":true,"settingDisableRenderRequestBody":false,"settingEncodeUrl":true,"settingRebuildPath":true,"settingFollowRedirects":"global","_type":"request"},{"_id":"req_08ba37544a9d4a2fa3393fdbbb561467","parentId":"fld_df69bce5d0924eee9e699baa6a30527f","modified":1669266877141,"created":1662175210785,"url":"http://localhost:3000/users","name":"Create User","description":"","method":"POST","body":{"mimeType":"application/json","text":"{\n\t\"name\" : \"lilith\",\n\t\"email\" : \"lilith@kenzie.com\",\n\t\"password\": \"1234\",\n\t\"isAdm\" : false\n}"},"parameters":[],"headers":[{"name":"Content-Type","value":"application/json","id":"pair_6ba42883bcd7408c88b5d87e5237ef3a"}],"authentication":{},"metaSortKey":-1662175210785,"isPrivate":false,"settingStoreCookies":true,"settingSendCookies":true,"settingDisableRenderRequestBody":false,"settingEncodeUrl":true,"settingRebuildPath":true,"settingFollowRedirects":"global","_type":"request"},{"_id":"env_a745c4e97231aba0635500fb6dd3f772e48221fa","parentId":"wrk_002d912e683a47ee8bedc851c7e13838","modified":1662175199114,"created":1662175199114,"name":"Base Environment","data":{},"dataPropertyOrder":null,"color":null,"isPrivate":false,"metaSortKey":1662175199114,"_type":"environment"},{"_id":"jar_a745c4e97231aba0635500fb6dd3f772e48221fa","parentId":"wrk_002d912e683a47ee8bedc851c7e13838","modified":1662175199146,"created":1662175199146,"name":"Default Jar","cookies":[],"_type":"cookie_jar"},{"_id":"spc_940166ffdebb4c268138aaa4e1b01d0b","parentId":"wrk_002d912e683a47ee8bedc851c7e13838","modified":1662175199022,"created":1662175199022,"fileName":"KL Imovveis","contents":"","contentType":"yaml","_type":"api_spec"}]}